casting/cast/core/__init__.py
casting/cast/core/digest.py
casting/cast/core/filelock.py
casting/cast/core/models.py
casting/cast/core/registry.py
casting/cast/core/scripts/__init__.py
casting/cast/core/scripts/rename_identifiers.py
casting/cast/core/yamlio.py
cast_core-0.1.2.dist-info/WHEEL
cast_core-0.1.2.dist-info/METADATA
cast_core-0.1.2.dist-info/RECORD
