Metadata-Version: 2.3
Name: cast-core
Version: 0.1.2
Summary: Core library for Cast Sync - parsing, normalization, digests
Requires-Dist: ruamel-yaml>=0.18.0
Requires-Dist: pydantic>=2.0.0
Requires-Dist: pytest>=8.3.0 ; extra == 'dev'
Requires-Python: >=3.13
Provides-Extra: dev
